apiaiWebhookSerializer/__init__.py
apiaiWebhookSerializer/request.py
apiaiWebhookSerializer/response.py
apiaiWebhookSerializer-0.2.0.dist-info/DESCRIPTION.rst
apiaiWebhookSerializer-0.2.0.dist-info/METADATA
apiaiWebhookSerializer-0.2.0.dist-info/RECORD
apiaiWebhookSerializer-0.2.0.dist-info/WHEEL
apiaiWebhookSerializer-0.2.0.dist-info/metadata.json
apiaiWebhookSerializer-0.2.0.dist-info/top_level.txt
